dibs_cli/__init__.py
dibs_cli/main.py
dibs_cli/dibscli_utils/__init__.py
dibs_cli/dibscli_utils/save_results.py
dibs_cli/dibscli_utils/validate_inputs.py
dibs_cli-1.0.1.dist-info/entry_points.txt
dibs_cli-1.0.1.dist-info/LICENSE
dibs_cli-1.0.1.dist-info/WHEEL
dibs_cli-1.0.1.dist-info/METADATA
dibs_cli-1.0.1.dist-info/RECORD
