Metadata-Version: 2.1
Name: dibs_cli
Version: 1.0.1
Summary: DIBS---Dynamic-ISO-Building-Simulator command line interface (CLI): DIBS---Dynamic-ISO-Building-Simulator is a simulation program for calculating the space heating, occupancy hot water, cooling and electricity demand of German non-residential buildings. Further the DIBS calculates the heating value based energy uses, the primary energy and the greenhouse gas emission. The underlying resistance-capacity-model is based on the simplified hourly method of ISO 13790:2008.
Keywords: Building,Building-Stock,Non-Domestic,Non-Residential,Operational,Energy,Greenhouse Gas,Global Warming Potential,Simulation,Model,Germany,ISO 13790,5R1C
Author: Simon Knoll, Michael Hörner
Author-email: Julian Bischof <j.bischof@iwu.de>, Wail Samjouni <w.samjouni@iwu.de>, André Müller <a.mueller@iwu.de>, Jens Calisti <j.calisti@iwu.de>
Requires-Python: >=3.10.0
Classifier: Development Status :: 4 - Beta
Classifier: Programming Language :: Python
Requires-Dist: rich
Requires-Dist: tqdm
Requires-Dist: typer
Requires-Dist: dibs_computing_core
Requires-Dist: dibs_datasource_csv
Requires-Dist: dibs_data
Project-URL: Repository, https://github.com/IWUGERMANY/DibsCLI
